flaregun/__init__.py
flaregun/flaregun.py
flaregun-0.0.2.dist-info/LICENSE
flaregun-0.0.2.dist-info/METADATA
flaregun-0.0.2.dist-info/WHEEL
flaregun-0.0.2.dist-info/RECORD
