Metadata-Version: 2.1
Name: flaregun
Version: 0.0.2
Summary: Tiny PyTorch helper package to get stats on GPU usage, model params, etc.
License: MIT
Author: Michael Wornow
Requires-Python: >=3.9
Classifier: License :: OSI Approved :: MIT License
Classifier: Programming Language :: Python :: 3
Classifier: Programming Language :: Python :: 3.9
Classifier: Programming Language :: Python :: 3.10
Classifier: Programming Language :: Python :: 3.11
Requires-Dist: pynvml (>=11.5.0)
